jquants_mcp_server/__init__.py
jquants_mcp_server/server.py
jquants_mcp_server-1.0.0.dist-info/METADATA
jquants_mcp_server-1.0.0.dist-info/WHEEL
jquants_mcp_server-1.0.0.dist-info/entry_points.txt
jquants_mcp_server-1.0.0.dist-info/licenses/LICENSE
jquants_mcp_server-1.0.0.dist-info/RECORD
