Metadata-Version: 2.4
Name: jquants-mcp-server
Version: 1.0.0
Summary: MCP server for J-Quants API - Access Japanese stock market data including prices, financial statements, and trading information
Project-URL: Homepage, https://github.com/kinoh/jquants-mcp-server
Project-URL: Repository, https://github.com/kinoh/jquants-mcp-server
Project-URL: Issues, https://github.com/kinoh/jquants-mcp-server/issues
Author-email: 㐂乃 <4271312+kinoh@users.noreply.github.com>
License-Expression: MIT
License-File: LICENSE
Keywords: finance,japan,jquants,market,mcp,stock
Classifier: Development Status :: 4 - Beta
Classifier: Intended Audience :: Developers
Classifier: License :: OSI Approved :: MIT License
Classifier: Programming Language :: Python :: 3
Classifier: Programming Language :: Python :: 3.13
Classifier: Topic :: Office/Business :: Financial
Classifier: Topic :: Software Development :: Libraries :: Python Modules
Requires-Python: >=3.13
Requires-Dist: jquants-api-client>=1.9.0
Requires-Dist: mcp>=1.7.1
Provides-Extra: dev
Requires-Dist: pytest>=7.0.0; extra == 'dev'
